{"Cell_0": {"Label1": "Eosinophil", "Label2": null, "x1": "3488", "x2": "4063", "y1": "846", "y2": "1421", "Cell_ID": "100_14.bmp"}, "Cell_1": {"Label1": "Eosinophil", "Label2": null, "x1": "2920", "x2": "3495", "y1": "207", "y2": "782", "Cell_ID": "100_9.bmp"}, "Cell_2": {"Label1": "Eosinophil", "Label2": null, "x1": "2767", "x2": "3342", "y1": "1665", "y2": "2240", "Cell_ID": "100_8.bmp"}, "Cell_3": {"Label1": "Eosinophil", "Label2": null, "x1": "2315", "x2": "2890", "y1": "1518", "y2": "2093", "Cell_ID": "100_5.bmp"}, "Cell_4": {"Label1": "Eosinophil", "Label2": null, "x1": "3462", "x2": "4037", "y1": "513", "y2": "1088", "Cell_ID": "100_12.bmp"}, "Cell_5": {"Label1": "Band", "Label2": null, "x1": "2226", "x2": "2801", "y1": "150", "y2": "725", "Cell_ID": "100_4.bmp"}, "Cell_6": {"Label1": "Eosinophil", "Label2": null, "x1": "3184", "x2": "3759", "y1": "790", "y2": "1365", "Cell_ID": "100_11.bmp"}, "Cell_7": {"Label1": "Monocyte", "Label2": null, "x1": "3692", "x2": "4267", "y1": "2073", "y2": "2648", "Cell_ID": "100_15.bmp"}, "Cell_8": {"Label1": "Eosinophil", "Label2": null, "x1": "2484", "x2": "3059", "y1": "1237", "y2": "1812", "Cell_ID": "100_6.bmp"}, "Cell_9": {"Label1": "Eosinophil", "Label2": null, "x1": "1760", "x2": "2335", "y1": "765", "y2": "1340", "Cell_ID": "100_1.bmp"}, "Cell_10": {"Label1": "Eosinophil", "Label2": null, "x1": "1729", "x2": "2304", "y1": "2352", "y2": "2927", "Cell_ID": "100_2.bmp"}, "Cell_11": {"Label1": "Unknn", "Label2": null, "x1": "3747", "x2": "4322", "y1": "912", "y2": "1487", "Cell_ID": "100_16.bmp"}, "Cell_12": {"Label1": "Neutrophil", "Label2": null, "x1": "2773", "x2": "3348", "y1": "2098", "y2": "2673", "Cell_ID": "100_7.bmp"}, "Cell_13": {"Label1": "Small Lymph", "Label2": null, "x1": "2088", "x2": "2663", "y1": "1443", "y2": "2018", "Cell_ID": "100_3.bmp"}, "Cell_14": {"Label1": "Eosinophil", "Label2": null, "x1": "3507", "x2": "4082", "y1": "1073", "y2": "1648", "Cell_ID": "100_13.bmp"}, "Zoom": "100x", "Stain Method": "Giemsa", "Film Label": "Normal-eosinophilia", "Camera": "Samsung Galaxy S5", "Microscop": "Olympus CX18", "Film ID": "95-8-29-1", "Cell Numbers": 15}