{"Cell_0": {"Label1": null, "Label2": null, "x1": "3840", "x2": "4415", "y1": "1073", "y2": "1648", "Cell_ID": "400_12.bmp"}, "Cell_1": {"Label1": null, "Label2": null, "x1": "3100", "x2": "3675", "y1": "1587", "y2": "2162", "Cell_ID": "400_9.bmp"}, "Cell_2": {"Label1": null, "Label2": null, "x1": "2401", "x2": "2976", "y1": "1268", "y2": "1843", "Cell_ID": "400_8.bmp"}, "Cell_3": {"Label1": null, "Label2": null, "x1": "3537", "x2": "4112", "y1": "1785", "y2": "2360", "Cell_ID": "400_11.bmp"}, "Cell_4": {"Label1": null, "Label2": null, "x1": "1761", "x2": "2336", "y1": "2413", "y2": "2988", "Cell_ID": "400_4.bmp"}, "Cell_5": {"Label1": null, "Label2": null, "x1": "2122", "x2": "2697", "y1": "1901", "y2": "2476", "Cell_ID": "400_6.bmp"}, "Cell_6": {"Label1": null, "Label2": null, "x1": "1582", "x2": "2157", "y1": "1188", "y2": "1763", "Cell_ID": "400_3.bmp"}, "Cell_7": {"Label1": null, "Label2": null, "x1": "2268", "x2": "2843", "y1": "1556", "y2": "2131", "Cell_ID": "400_7.bmp"}, "Cell_8": {"Label1": null, "Label2": null, "x1": "1823", "x2": "2398", "y1": "1782", "y2": "2357", "Cell_ID": "400_5.bmp"}, "Cell_9": {"Label1": null, "Label2": null, "x1": "1438", "x2": "2013", "y1": "2065", "y2": "2640", "Cell_ID": "400_2.bmp"}, "Cell_10": {"Label1": null, "Label2": null, "x1": "3304", "x2": "3879", "y1": "792", "y2": "1367", "Cell_ID": "400_10.bmp"}, "Zoom": "100x", "Stain Method": "Giemsa", "Film Label": "Normal-eosinophilia", "Camera": "Samsung Galaxy S5", "Microscop": "Olympus CX18", "Film ID": "95-8-29-1", "Cell Numbers": 11}