{"Cell_0": {"Label1": "Large Lymph", "Label2": "Large Lymph", "x1": "3090", "x2": "3665", "y1": "1335", "y2": "1910", "Cell_ID": "51_2.bmp"}, "Cell_1": {"Label1": "Eosinophil", "Label2": "Eosinophil", "x1": "3360", "x2": "3935", "y1": "1142", "y2": "1717", "Cell_ID": "51_3.bmp"}, "Cell_2": {"Label1": "Eosinophil", "Label2": "Eosinophil", "x1": "2569", "x2": "3144", "y1": "1657", "y2": "2232", "Cell_ID": "51_1.bmp"}, "Zoom": "100x", "Stain Method": "Giemsa", "Film Label": "Normal-eosinophilia", "Camera": "Samsung Galaxy S5", "Microscop": "Olympus CX18", "Film ID": "95-8-27-1", "Cell Numbers": 3}