{"Cell_0": {"Label1": null, "Label2": null, "x1": "1755", "x2": "2330", "y1": "568", "y2": "1143", "Cell_ID": "208_3.bmp"}, "Cell_1": {"Label1": null, "Label2": null, "x1": "3643", "x2": "4218", "y1": "2015", "y2": "2590", "Cell_ID": "208_10.bmp"}, "Cell_2": {"Label1": null, "Label2": null, "x1": "3722", "x2": "4297", "y1": "1670", "y2": "2245", "Cell_ID": "208_11.bmp"}, "Cell_3": {"Label1": null, "Label2": null, "x1": "2796", "x2": "3371", "y1": "1485", "y2": "2060", "Cell_ID": "208_7.bmp"}, "Cell_4": {"Label1": null, "Label2": null, "x1": "2226", "x2": "2801", "y1": "692", "y2": "1267", "Cell_ID": "208_4.bmp"}, "Cell_5": {"Label1": null, "Label2": null, "x1": "3800", "x2": "4375", "y1": "244", "y2": "819", "Cell_ID": "208_12.bmp"}, "Cell_6": {"Label1": null, "Label2": null, "x1": "1703", "x2": "2278", "y1": "850", "y2": "1425", "Cell_ID": "208_2.bmp"}, "Cell_7": {"Label1": null, "Label2": null, "x1": "3137", "x2": "3712", "y1": "1409", "y2": "1984", "Cell_ID": "208_8.bmp"}, "Cell_8": {"Label1": null, "Label2": null, "x1": "2784", "x2": "3359", "y1": "551", "y2": "1126", "Cell_ID": "208_5.bmp"}, "Cell_9": {"Label1": null, "Label2": null, "x1": "2802", "x2": "3377", "y1": "1739", "y2": "2314", "Cell_ID": "208_6.bmp"}, "Cell_10": {"Label1": null, "Label2": null, "x1": "1209", "x2": "1784", "y1": "1538", "y2": "2113", "Cell_ID": "208_1.bmp"}, "Zoom": "100x", "Stain Method": "Giemsa", "Film Label": "Normal-eosinophilia", "Camera": "Samsung Galaxy S5", "Microscop": "Olympus CX18", "Film ID": "95-8-29-1", "Cell Numbers": 11}