{"Cell_0": {"Label1": "Unknn", "Label2": null, "x1": "3074", "x2": "3649", "y1": "1243", "y2": "1818", "Cell_ID": "169_9.bmp"}, "Cell_1": {"Label1": "Eosinophil", "Label2": null, "x1": "2396", "x2": "2971", "y1": "2051", "y2": "2626", "Cell_ID": "169_6.bmp"}, "Cell_2": {"Label1": "Eosinophil", "Label2": null, "x1": "2774", "x2": "3349", "y1": "1285", "y2": "1860", "Cell_ID": "169_8.bmp"}, "Cell_3": {"Label1": "Eosinophil", "Label2": null, "x1": "3801", "x2": "4376", "y1": "1550", "y2": "2125", "Cell_ID": "169_12.bmp"}, "Cell_4": {"Label1": "Burst", "Label2": null, "x1": "2101", "x2": "2676", "y1": "451", "y2": "1026", "Cell_ID": "169_4.bmp"}, "Cell_5": {"Label1": "Unknn", "Label2": null, "x1": "1923", "x2": "2498", "y1": "940", "y2": "1515", "Cell_ID": "169_3.bmp"}, "Cell_6": {"Label1": "Eosinophil", "Label2": null, "x1": "1626", "x2": "2201", "y1": "1257", "y2": "1832", "Cell_ID": "169_2.bmp"}, "Cell_7": {"Label1": "Eosinophil", "Label2": null, "x1": "3202", "x2": "3777", "y1": "694", "y2": "1269", "Cell_ID": "169_10.bmp"}, "Cell_8": {"Label1": "Eosinophil", "Label2": null, "x1": "2393", "x2": "2968", "y1": "2301", "y2": "2876", "Cell_ID": "169_7.bmp"}, "Cell_9": {"Label1": "Burst", "Label2": null, "x1": "2144", "x2": "2719", "y1": "735", "y2": "1310", "Cell_ID": "169_5.bmp"}, "Zoom": "100x", "Stain Method": "Giemsa", "Film Label": "Normal-eosinophilia", "Camera": "Samsung Galaxy S5", "Microscop": "Olympus CX18", "Film ID": "95-8-29-1", "Cell Numbers": 10}