{"Cell_0": {"Label1": "Burst", "Label2": "Burst", "x1": "2633", "x2": "3208", "y1": "801", "y2": "1376", "Cell_ID": "470_1.bmp"}, "Cell_1": {"Label1": "Burst", "Label2": "Burst", "x1": "2695", "x2": "3270", "y1": "571", "y2": "1146", "Cell_ID": "470_2.bmp"}, "Cell_2": {"Label1": "Monocyte", "Label2": "Monocyte", "x1": "3156", "x2": "3731", "y1": "1176", "y2": "1751", "Cell_ID": "470_3.bmp"}, "Zoom": "100x", "Stain Method": "Giemsa", "Film Label": "Normal", "Camera": "Samsung Galaxy S5", "Microscop": "Olympus CX18", "Film ID": "95-5-13-1", "Cell Numbers": 3}