{"Cell_0": {"Label1": "Neutrophil", "Label2": "Neutrophil", "x1": "2674", "x2": "3249", "y1": "659", "y2": "1234", "Cell_ID": "128_2.bmp"}, "Cell_1": {"Label1": "Neutrophil", "Label2": "Neutrophil", "x1": "2219", "x2": "2794", "y1": "1074", "y2": "1649", "Cell_ID": "128_1.bmp"}, "Cell_2": {"Label1": "Neutrophil", "Label2": "Neutrophil", "x1": "2910", "x2": "3485", "y1": "2037", "y2": "2612", "Cell_ID": "128_3.bmp"}, "Zoom": "100x", "Stain Method": "Giemsa", "Film Label": "Normal", "Camera": "Samsung Galaxy S5", "Microscop": "Olympus CX18", "Film ID": "95-8-10-1", "Cell Numbers": 3}