{"Cell_0": {"Label1": "Large Lymph", "Label2": "Large Lymph", "x1": "2049", "x2": "2624", "y1": "1370", "y2": "1945", "Cell_ID": "300_3.bmp"}, "Cell_1": {"Label1": "Neutrophil", "Label2": "Neutrophil", "x1": "2894", "x2": "3469", "y1": "1709", "y2": "2284", "Cell_ID": "300_4.bmp"}, "Cell_2": {"Label1": "Large Lymph", "Label2": "Large Lymph", "x1": "1172", "x2": "1747", "y1": "1266", "y2": "1841", "Cell_ID": "300_1.bmp"}, "Cell_3": {"Label1": "Monocyte", "Label2": "Monocyte", "x1": "2075", "x2": "2650", "y1": "1031", "y2": "1606", "Cell_ID": "300_2.bmp"}, "Cell_4": {"Label1": "Neutrophil", "Label2": "Neutrophil", "x1": "2946", "x2": "3521", "y1": "410", "y2": "985", "Cell_ID": "300_5.bmp"}, "Zoom": "100x", "Stain Method": "Giemsa", "Film Label": "Normal", "Camera": "Samsung Galaxy S5", "Microscop": "Olympus CX18", "Film ID": "95-8-13-4", "Cell Numbers": 5}