{"Cell_0": {"Label1": "Monocyte", "Label2": "Monocyte", "x1": "1622", "x2": "2197", "y1": "413", "y2": "988", "Cell_ID": "454_2.bmp"}, "Cell_1": {"Label1": "Artifact", "Label2": "Artifact", "x1": "1132", "x2": "1707", "y1": "609", "y2": "1184", "Cell_ID": "454_1.bmp"}, "Cell_2": {"Label1": "Unknn", "Label2": "Unknn", "x1": "2913", "x2": "3488", "y1": "959", "y2": "1534", "Cell_ID": "454_3.bmp"}, "Zoom": "100x", "Stain Method": "Giemsa", "Film Label": "Normal", "Camera": "Samsung Galaxy S5", "Microscop": "Olympus CX18", "Film ID": "95-8-10-1", "Cell Numbers": 3}