{"Cell_0": {"Label1": null, "Label2": null, "x1": "2175", "x2": "2750", "y1": "2335", "y2": "2910", "Cell_ID": "81_5.bmp"}, "Cell_1": {"Label1": null, "Label2": null, "x1": "2575", "x2": "3150", "y1": "412", "y2": "987", "Cell_ID": "81_6.bmp"}, "Cell_2": {"Label1": null, "Label2": null, "x1": "1941", "x2": "2516", "y1": "885", "y2": "1460", "Cell_ID": "81_3.bmp"}, "Cell_3": {"Label1": null, "Label2": null, "x1": "1663", "x2": "2238", "y1": "1911", "y2": "2486", "Cell_ID": "81_1.bmp"}, "Cell_4": {"Label1": null, "Label2": null, "x1": "2770", "x2": "3345", "y1": "1435", "y2": "2010", "Cell_ID": "81_7.bmp"}, "Cell_5": {"Label1": null, "Label2": null, "x1": "2893", "x2": "3468", "y1": "1706", "y2": "2281", "Cell_ID": "81_8.bmp"}, "Cell_6": {"Label1": null, "Label2": null, "x1": "3537", "x2": "4112", "y1": "1340", "y2": "1915", "Cell_ID": "81_10.bmp"}, "Cell_7": {"Label1": null, "Label2": null, "x1": "2138", "x2": "2713", "y1": "596", "y2": "1171", "Cell_ID": "81_4.bmp"}, "Zoom": "100x", "Stain Method": "Giemsa", "Film Label": "Normal-eosinophilia", "Camera": "Samsung Galaxy S5", "Microscop": "Olympus CX18", "Film ID": "95-8-29-1", "Cell Numbers": 8}