{"Cell_0": {"Label1": null, "Label2": null, "x1": "2991", "x2": "3566", "y1": "701", "y2": "1276", "Cell_ID": "245_14.bmp"}, "Cell_1": {"Label1": null, "Label2": null, "x1": "3169", "x2": "3744", "y1": "1578", "y2": "2153", "Cell_ID": "245_17.bmp"}, "Cell_2": {"Label1": null, "Label2": null, "x1": "2050", "x2": "2625", "y1": "413", "y2": "988", "Cell_ID": "245_5.bmp"}, "Cell_3": {"Label1": null, "Label2": null, "x1": "2422", "x2": "2997", "y1": "56", "y2": "631", "Cell_ID": "245_7.bmp"}, "Cell_4": {"Label1": null, "Label2": null, "x1": "1881", "x2": "2456", "y1": "1664", "y2": "2239", "Cell_ID": "245_3.bmp"}, "Cell_5": {"Label1": null, "Label2": null, "x1": "2298", "x2": "2873", "y1": "497", "y2": "1072", "Cell_ID": "245_6.bmp"}, "Cell_6": {"Label1": null, "Label2": null, "x1": "2064", "x2": "2639", "y1": "1207", "y2": "1782", "Cell_ID": "245_4.bmp"}, "Cell_7": {"Label1": null, "Label2": null, "x1": "1632", "x2": "2207", "y1": "1879", "y2": "2454", "Cell_ID": "245_1.bmp"}, "Cell_8": {"Label1": null, "Label2": null, "x1": "4125", "x2": "4700", "y1": "1002", "y2": "1577", "Cell_ID": "245_21.bmp"}, "Cell_9": {"Label1": null, "Label2": null, "x1": "2644", "x2": "3219", "y1": "807", "y2": "1382", "Cell_ID": "245_11.bmp"}, "Cell_10": {"Label1": null, "Label2": null, "x1": "2840", "x2": "3415", "y1": "2270", "y2": "2845", "Cell_ID": "245_13.bmp"}, "Cell_11": {"Label1": null, "Label2": null, "x1": "3078", "x2": "3653", "y1": "2360", "y2": "2935", "Cell_ID": "245_16.bmp"}, "Cell_12": {"Label1": null, "Label2": null, "x1": "2450", "x2": "3025", "y1": "933", "y2": "1508", "Cell_ID": "245_9.bmp"}, "Cell_13": {"Label1": null, "Label2": null, "x1": "4036", "x2": "4611", "y1": "580", "y2": "1155", "Cell_ID": "245_20.bmp"}, "Cell_14": {"Label1": null, "Label2": null, "x1": "2637", "x2": "3212", "y1": "2101", "y2": "2676", "Cell_ID": "245_12.bmp"}, "Cell_15": {"Label1": null, "Label2": null, "x1": "3073", "x2": "3648", "y1": "177", "y2": "752", "Cell_ID": "245_15.bmp"}, "Cell_16": {"Label1": null, "Label2": null, "x1": "1669", "x2": "2244", "y1": "1131", "y2": "1706", "Cell_ID": "245_2.bmp"}, "Cell_17": {"Label1": null, "Label2": null, "x1": "2448", "x2": "3023", "y1": "2344", "y2": "2919", "Cell_ID": "245_8.bmp"}, "Cell_18": {"Label1": null, "Label2": null, "x1": "3988", "x2": "4563", "y1": "1948", "y2": "2523", "Cell_ID": "245_19.bmp"}, "Zoom": "100x", "Stain Method": "Giemsa", "Film Label": "Normal-eosinophilia", "Camera": "Samsung Galaxy S5", "Microscop": "Olympus CX18", "Film ID": "95-8-29-1", "Cell Numbers": 19}