{"Cell_0": {"Label1": "Eosinophil", "Label2": null, "x1": "1859", "x2": "2434", "y1": "197", "y2": "772", "Cell_ID": "128_2.bmp"}, "Cell_1": {"Label1": "Burst", "Label2": null, "x1": "3289", "x2": "3864", "y1": "2129", "y2": "2704", "Cell_ID": "128_6.bmp"}, "Cell_2": {"Label1": "Not centered", "Label2": null, "x1": "4283", "x2": "4858", "y1": "634", "y2": "1209", "Cell_ID": "128_8.bmp"}, "Cell_3": {"Label1": "Eosinophil", "Label2": null, "x1": "2081", "x2": "2656", "y1": "1182", "y2": "1757", "Cell_ID": "128_4.bmp"}, "Cell_4": {"Label1": "Band", "Label2": null, "x1": "2517", "x2": "3092", "y1": "2397", "y2": "2972", "Cell_ID": "128_5.bmp"}, "Cell_5": {"Label1": "Eosinophil", "Label2": null, "x1": "1714", "x2": "2289", "y1": "2016", "y2": "2591", "Cell_ID": "128_1.bmp"}, "Cell_6": {"Label1": "Burst", "Label2": null, "x1": "3446", "x2": "4021", "y1": "118", "y2": "693", "Cell_ID": "128_7.bmp"}, "Zoom": "100x", "Stain Method": "Giemsa", "Film Label": "Normal-eosinophilia", "Camera": "Samsung Galaxy S5", "Microscop": "Olympus CX18", "Film ID": "95-8-29-1", "Cell Numbers": 7}