{"Cell_0": {"Label1": null, "Label2": null, "x1": "2749", "x2": "3324", "y1": "484", "y2": "1059", "Cell_ID": "725_6.bmp"}, "Cell_1": {"Label1": null, "Label2": null, "x1": "2128", "x2": "2703", "y1": "1910", "y2": "2485", "Cell_ID": "725_3.bmp"}, "Cell_2": {"Label1": null, "Label2": null, "x1": "1882", "x2": "2457", "y1": "1893", "y2": "2468", "Cell_ID": "725_1.bmp"}, "Cell_3": {"Label1": null, "Label2": null, "x1": "3649", "x2": "4224", "y1": "44", "y2": "619", "Cell_ID": "725_7.bmp"}, "Cell_4": {"Label1": null, "Label2": null, "x1": "2496", "x2": "3071", "y1": "1869", "y2": "2444", "Cell_ID": "725_4.bmp"}, "Cell_5": {"Label1": null, "Label2": null, "x1": "1913", "x2": "2488", "y1": "978", "y2": "1553", "Cell_ID": "725_2.bmp"}, "Zoom": "100x", "Stain Method": "Giemsa", "Film Label": "Normal-eosinophilia", "Camera": "Samsung Galaxy S5", "Microscop": "Olympus CX18", "Film ID": "95-8-29-1", "Cell Numbers": 6}