{"Cell_0": {"Label1": null, "Label2": null, "x1": "1979", "x2": "2554", "y1": "2121", "y2": "2696", "Cell_ID": "711_4.bmp"}, "Cell_1": {"Label1": null, "Label2": null, "x1": "1646", "x2": "2221", "y1": "1636", "y2": "2211", "Cell_ID": "711_3.bmp"}, "Cell_2": {"Label1": null, "Label2": null, "x1": "1545", "x2": "2120", "y1": "1136", "y2": "1711", "Cell_ID": "711_2.bmp"}, "Cell_3": {"Label1": null, "Label2": null, "x1": "3157", "x2": "3732", "y1": "0", "y2": "575", "Cell_ID": "711_11.bmp"}, "Cell_4": {"Label1": null, "Label2": null, "x1": "3391", "x2": "3966", "y1": "1539", "y2": "2114", "Cell_ID": "711_13.bmp"}, "Cell_5": {"Label1": null, "Label2": null, "x1": "2109", "x2": "2684", "y1": "907", "y2": "1482", "Cell_ID": "711_6.bmp"}, "Cell_6": {"Label1": null, "Label2": null, "x1": "1480", "x2": "2055", "y1": "1604", "y2": "2179", "Cell_ID": "711_1.bmp"}, "Cell_7": {"Label1": null, "Label2": null, "x1": "2847", "x2": "3422", "y1": "1841", "y2": "2416", "Cell_ID": "711_8.bmp"}, "Zoom": "100x", "Stain Method": "Giemsa", "Film Label": "Normal-eosinophilia", "Camera": "Samsung Galaxy S5", "Microscop": "Olympus CX18", "Film ID": "95-8-29-1", "Cell Numbers": 8}